README.md
setup.py
qth_openwrt_status/__init__.py
qth_openwrt_status/version.py
qth_openwrt_status.egg-info/PKG-INFO
qth_openwrt_status.egg-info/SOURCES.txt
qth_openwrt_status.egg-info/dependency_links.txt
qth_openwrt_status.egg-info/entry_points.txt
qth_openwrt_status.egg-info/requires.txt
qth_openwrt_status.egg-info/top_level.txt