Metadata-Version: 1.1
Name: qth-openwrt-status
Version: 0.1.0
Summary: A Qth interface monitoring a subset of OpenWRT router status..
Home-page: https://github.com/mossblaser/qth_openwrt_status
Author: Jonathan Heathcote
Author-email: UNKNOWN
License: GPLv2
Keywords: home-automation
Platform: UNKNOWN
Classifier: Development Status :: 3 - Alpha
Classifier: Intended Audience :: Developers
Classifier: License :: OSI Approved :: GNU General Public License v2 (GPLv2)
Classifier: Operating System :: POSIX :: Linux
Classifier: Operating System :: Microsoft :: Windows
Classifier: Operating System :: MacOS
Classifier: Programming Language :: Python :: 3
Classifier: Programming Language :: Python :: 3.4
Classifier: Programming Language :: Python :: 3.5
